get_full_year.py
get_full_year-0.1.0.dist-info/METADATA
get_full_year-0.1.0.dist-info/WHEEL
get_full_year-0.1.0.dist-info/top_level.txt
get_full_year-0.1.0.dist-info/RECORD
