Metadata-Version: 2.1
Name: get-full-year
Version: 0.1.0
Summary: getfullyear SDK for Python
Requires-Python: >=3.8
Requires-Dist: requests>=2.32.3
